etoile_pixtral_description/__init__.py
etoile_pixtral_description/models.py
etoile_pixtral_description/prompts.py
etoile_pixtral_description-2025.5.160702.dist-info/METADATA
etoile_pixtral_description-2025.5.160702.dist-info/WHEEL
etoile_pixtral_description-2025.5.160702.dist-info/top_level.txt
etoile_pixtral_description-2025.5.160702.dist-info/RECORD
