Metadata-Version: 2.4
Name: etoile_pixtral_description
Version: 2025.5.160702
Home-page: 
Author: Eugene Evstafev
Author-email: chigwel@gmail.com
License: MIT
Classifier: License :: OSI Approved :: MIT License
Classifier: Development Status :: 3 - Alpha
Classifier: Intended Audience :: Developers
Classifier: Programming Language :: Python :: 3
Classifier: Operating System :: OS Independent
Requires-Python: >=3.6
Requires-Dist: langchain==0.1.20
Requires-Dist: langchain-core==0.1.52
Requires-Dist: langchain-community==0.0.38
Requires-Dist: langchain-huggingface==0.0.3
Dynamic: author
Dynamic: author-email
Dynamic: classifier
Dynamic: description
Dynamic: description-content-type
Dynamic: license
Dynamic: requires-dist
Dynamic: requires-python
